pgmanage/__init__.py
pgmanage/connect_async.py
pgmanage/test.py
pgmanage/异步测试1.py
pgmanage/异步测试2.0.py
pgmanage/asyncpg/__init__.py
pgmanage/asyncpg/connect.py
pgmanage/asyncpg/dbexec.py
pgmanage/syncpg/__init__.py
pgmanage/syncpg/connect.py
pgmanage/syncpg/copyto2.py
pgmanage/syncpg/copyto3.py
pgmanage/syncpg/dbexec.py
pgmanage-2.0.2.dist-info/licenses/LICENSE
test/__init__.py
test/async_connect.py
test/async_dbexec.py
test/sync_connect.py
test/sync_dbexec.py
pgmanage-2.0.2.dist-info/METADATA
pgmanage-2.0.2.dist-info/WHEEL
pgmanage-2.0.2.dist-info/top_level.txt
pgmanage-2.0.2.dist-info/RECORD
