Metadata-Version: 2.4
Name: pgmanage
Version: 2.0.2
Summary: pgsql数据库工具
Home-page: https://gitee.com/manjim/pgmanage
Author: manji
Author-email: pnsm@qq.com
Classifier: Programming Language :: Python :: 3
Classifier: License :: OSI Approved :: MIT License
Classifier: Operating System :: OS Independent
Requires-Python: >=3
License-File: LICENSE
Requires-Dist: psycopg[binary,pool]
Dynamic: author
Dynamic: author-email
Dynamic: classifier
Dynamic: description
Dynamic: description-content-type
Dynamic: home-page
Dynamic: license-file
Dynamic: requires-dist
Dynamic: requires-python
Dynamic: summary
